{
  "title": "114 年國中教育會考 - 社會",
  "year": "114",
  "subject": "社會",
  "duration": 70,
  "questions": [
    {
      "number": 1,
      "text": "一國若發生重大自然災害，可能會直接衝擊該國的經濟活動，而成為較脆弱的投資環境。臺灣因位於地震帶常發生地震，且易受颱風侵襲，於2015年被某金融機構列為最脆弱的十個國家之一。下列哪一國家最可能也因為常發生上述二種自然災害而列名其中？",
      "passage": "",
      "options": [
        "日本",
        "伊朗",
        "北韓",
        "澳洲"
      ],
      "answer": "A",
      "type": "single",
      "audio": "",
      "score": 2
    },
    {
      "number": 2,
      "text": "2019年底，臺灣的農場與牧場，正式迎來首批合法的農業移工，其中2名是酪農移工，其餘5名則是外展農業移工。外展農業移工意指由農會、漁會、農林漁牧有關之合作社，或非營利組織等「外展機構」所聘僱的外國人，並由外展機構指派其至服務的場所從事農務工作。上述政策的推行主要是為了因應下列何項問題？",
      "passage": "",
      "options": [
        "農業勞動力老化",
        "農產品的安全性",
        "農村失業率偏高",
        "稻米的生產過剩"
      ],
      "answer": "A",
      "type": "single",
      "audio": "",
      "score": 2
    },
    {
      "number": 3,
      "text": "某部電影描述主角與母親及只會說華語的祖母，同住在美國舊金山華人聚集的街區，並出現拿筷子吃飯、與家人共度春節及清明節等原鄉文化情節，而主角雖然從小在美國長大，但在生活中仍經常使用華語。上述電影情節的文化意涵及傳播方式，與下列何者呈現的概念最相近？",
      "passage": "",
      "options": [
        "利用國際婦女節倡導家務分工性別平權理念",
        "來自泰、緬的新住民與移工齊聚慶祝潑水節",
        "推行國語運動貶低母語所產生的不平等現象",
        "華人認為烏鴉象徵厄運，在日本則象徵吉祥"
      ],
      "answer": "B",
      "type": "single",
      "audio": "",
      "score": 2
    },
    {
      "number": 4,
      "text": "某行政區內名為「挖仔」的聚落地圖，1904年臺灣堡圖顯示其位於河道旁的彎曲處。根據該聚落所處環境特色判斷，其地名代表的意義最可能為下列何者？<br><img src=\"/images/cap/114/社會/114_社會_試題.pdf-0002-13.webp\" style=\"max-width:100%; display:block; margin:10px 0;\"><br><img src=\"/images/cap/114/社會/114_社會_試題.pdf-0002-14.webp\" style=\"max-width:100%; display:block; margin:10px 0;\">",
      "passage": "",
      "options": [
        "位於岬灣海岸的灣澳",
        "鄰近溪流河道的轉彎處",
        "位處高山之間的小谷地",
        "台地上的低窪地蓄水成湖"
      ],
      "answer": "B",
      "type": "single",
      "audio": "",
      "score": 2
    },
    {
      "number": 5,
      "text": "某研究於2018年調查發現，臺灣不同地區民眾對於各種社會議題的關注傾向與程度有所差異，其中部分地區的民眾對於自身周遭環境的議題更加關切，例如離島地區。下列何者最可能為離島地區民眾較為關注的議題？",
      "passage": "",
      "options": [
        "適當管制房價，降低民眾租屋或購屋的負擔",
        "落實區域間資源分配，讓民眾獲得同等醫療品質",
        "管制重工業廢水的排放，避免造成土壤重金屬汙染",
        "大規模土石流或崩塌，可能導致建築物毀損及人員傷亡\n\n---"
      ],
      "answer": "B",
      "type": "single",
      "audio": "",
      "score": 2
    },
    {
      "number": 6,
      "text": "圖為臺灣歷史上某地區的地圖，圖中標示了「臺灣總督府」、「帝國大學」、「鐵道部工場」、「飛行場」與「臺灣神社」。根據內容判斷，此圖最有可能出自下列何者？<br><img src=\"/images/cap/114/社會/114_社會_試題.pdf-0003-02.webp\" style=\"max-width:100%; display:block; margin:10px 0;\"><br><img src=\"/images/cap/114/社會/114_社會_試題.pdf-0003-03.webp\" style=\"max-width:100%; display:block; margin:10px 0;\">",
      "passage": "",
      "options": [
        "大航海時代的〈熱蘭遮城鎮鳥瞰圖〉",
        "清帝國統治時期的《淡水廳志》",
        "日本統治時期的〈臺北州大觀〉",
        "戰後臺灣的《最新版臺灣街道圖》"
      ],
      "answer": "C",
      "type": "single",
      "audio": "",
      "score": 2
    },
    {
      "number": 7,
      "text": "中國史上某作家發表了一部著作，他在書中提倡女性應當恢復的自然權利：一、入學之權利；二、交友之權利；三、營業之權利；四、掌握財產之權利；五、出入自由之權利；六、婚姻自由之權利。該著作所提倡的主張，最可能與下列何者有關？<br><img src=\"/images/cap/114/社會/114_社會_試題.pdf-0003-09.webp\" style=\"max-width:100%; display:block; margin:10px 0;\">",
      "passage": "",
      "options": [
        "隋唐時期，西域民族風俗傳入中國",
        "宋元時期，朱熹學術成就受到推崇",
        "明末清初，中國引入西方科學知識",
        "晚清時期，近代歐洲思潮傳入中國"
      ],
      "answer": "D",
      "type": "single",
      "audio": "",
      "score": 2
    },
    {
      "number": 8,
      "text": "「十一世紀時，旅居中國的穆斯林商人，在生活方面可以依照自身的習俗行事，例如他們在廣州的清真寺高塔上，懸掛旗幟、燈火來指引船隻出入港口。但在貿易方面，仍須受到官方機構的管轄，此機構負責收取關稅、接運貢品，並執行香料、珊瑚及象牙等進口商品的專賣，監督商家船隻的活動。」上述的「機構」最可能是下列何者？",
      "passage": "",
      "options": [
        "洋行",
        "驛站",
        "市舶司",
        "總理各國事務衙門"
      ],
      "answer": "C",
      "type": "single",
      "audio": "",
      "score": 2
    },
    {
      "number": 9,
      "text": "「巴黎和會引起中國強烈的民族情緒，在部分知識分子的心中，西方角色從啟蒙者轉變為壓迫者，因此他們逐漸對維護帝國主義、資本主義的西方國家感到失望。在五四運動後，有些知識分子開始轉向世界革命理論，試圖從俄國革命家對於受壓迫民族的呼籲，以及俄國新政權宣布放棄沙皇時代在中國特權的聲明中，找到改變中國的出路。」上述內容最可能與下列何者有關？",
      "passage": "",
      "options": [
        "中華民國的建立",
        "西安事變的發生",
        "中國共產黨的成立",
        "文化大革命的發動"
      ],
      "answer": "C",
      "type": "single",
      "audio": "",
      "score": 2
    },
    {
      "number": 10,
      "text": "一幅歷史上的木刻版畫，畫中將羅馬教宗等神職人員畫成新約聖經中七個頭的怪獸，並有標語「滿滿一袋赦罪，用錢來贖」，以及魔鬼躲在教會奉獻箱底部探頭張望。根據畫中內容判斷，作者的立場最可能是下列何者？<br><img src=\"/images/cap/114/社會/114_社會_試題.pdf-0003-18.webp\" style=\"max-width:100%; display:block; margin:10px 0;\">",
      "passage": "",
      "options": [
        "強調君士坦丁堡教會擁有基督教的領導權",
        "支持路德教派所提出因信得救的信仰主張",
        "主張只有希伯來民族能作為耶和華的選民",
        "認同羅耀拉等人所提倡天主教改革的理念\n\n---"
      ],
      "answer": "B",
      "type": "single",
      "audio": "",
      "score": 2
    },
    {
      "number": 11,
      "text": "一間跨國咖啡公司打算在某國的傳統文化觀光區設立分店，但卻因為品牌形象與當地建築、傳統飲食習慣不同而引發居民抗議。該公司為此改變店面沿用的品牌風格，除了採用相容於該區環境的色系，還將原本的英文招牌改用當地文字呈現，並增加販售具當地料理特色的創意餐點，希望透過這些舉動降低當地的反彈聲浪。上述跨國公司的舉動，與下列何者最相符？",
      "passage": "",
      "options": [
        "成立跨國企業，強化國際分工",
        "憑藉強勢文化，推動產業轉型",
        "尊重多元文化，促進文化融合",
        "凝聚社區認同，發展社區組織"
      ],
      "answer": "C",
      "type": "single",
      "audio": "",
      "score": 2
    },
    {
      "number": 12,
      "text": "美國於2022年6月21日起，禁止進口來自中國新疆的商品，因為美國政府認為這些商品是強迫維吾爾人勞動的產物。如果企業想要繼續將在新疆生產的商品出口至美國，則必須提出充足的證據，證明商品的生產過程沒有涉及強迫勞動問題。美國執行上述管制措施的主要理由，最可能是下列何者？",
      "passage": "",
      "options": [
        "擴大對外貿易的出超金額",
        "減少全球化下的貿易障礙",
        "保障旅外國民的工作權益",
        "避免侵害人權的商業行為"
      ],
      "answer": "D",
      "type": "single",
      "audio": "",
      "score": 2
    },
    {
      "number": 13,
      "text": "某大學於學期末時，在校內美食街設立意見回饋箱，消費者有任何建議都可以寫在意見單上投入回饋箱中，學校會參考這些回饋的意見，藉以改善未來美食街的營運方式。根據上述內容判斷，下列何項回饋意見最能提升市場的競爭程度？",
      "passage": "",
      "options": [
        "廠商應提供校內師生購買餐點九折優惠",
        "應要求廠商提供餐點食材的生產履歷證明",
        "希望廠商販售份量較少且價格較便宜的餐點",
        "學校應招募更多廠商進駐美食街提供多元餐點"
      ],
      "answer": "D",
      "type": "single",
      "audio": "",
      "score": 2
    },
    {
      "number": 14,
      "text": "一對姊妹先後結婚了，圖示呈現她們（乙、丙為姊妹）各自與配偶（甲與乙結婚、丙與丁結婚）的關係。根據圖中內容判斷，甲、乙、丙、丁四人之間最不可能存在下列何種親屬關係？<br><img src=\"/images/cap/114/社會/114_社會_試題.pdf-0004-10.webp\" style=\"max-width:100%; display:block; margin:10px 0;\"><br><img src=\"/images/cap/114/社會/114_社會_試題.pdf-0004-11.webp\" style=\"max-width:100%; display:block; margin:10px 0;\">",
      "passage": "",
      "options": [
        "配偶",
        "姻親",
        "直系血親",
        "旁系血親"
      ],
      "answer": "C",
      "type": "single",
      "audio": "",
      "score": 2
    },
    {
      "number": 15,
      "text": "恬恬為了製作課堂報告所蒐集的資料，統計針對某候選人的新聞在各電視臺報導時間中所占比例。\n\n| 電視臺 | 總比例 | 正面報導 | 負面報導 |\n|---|---|---|---|\n| 水果臺 | 36% | 28% | 4% |\n| F News | 12% | 4% | 6% |\n| 水新聞 | 7% | 3% | 2% |\n| W電視 | 28% | 4% | 21% |\n*(統計時間: 5/1-5/7每日19:00~20:00的新聞)*\n\n根據表中資料判斷，下列何者最可能是恬恬探究這份資料後，建議閱聽人應注意的事項？",
      "passage": "",
      "options": [
        "覺察媒體的報導內容與事實不符",
        "解讀媒體報導中的性別刻板印象",
        "留意媒體業者是否持有特定的立場",
        "關注媒體是否善盡監督政府的責任\n\n---"
      ],
      "answer": "C",
      "type": "single",
      "audio": "",
      "score": 2
    },
    {
      "number": 16,
      "text": "中國於2019至2025年間規劃推動的「西部陸海新通道」，該通道利用鐵路、公路及海運等多種運輸方式（路線由成都、重慶往南連至南寧及沿海港口）以促進物流效率與經濟發展。根據圖中資訊判斷，上述通道的推動最可能具有下列何項效益？<br><img src=\"/images/cap/114/社會/114_社會_試題.pdf-0005-00.webp\" style=\"max-width:100%; display:block; margin:10px 0;\"><br><img src=\"/images/cap/114/社會/114_社會_試題.pdf-0005-06.webp\" style=\"max-width:100%; display:block; margin:10px 0;\">",
      "passage": "",
      "options": [
        "連結經北極海通往歐洲的航線",
        "節省與美墨加協定成員的海運時間",
        "增進與東南亞國協成員的貿易往來",
        "避免來自西亞的石油運輸受制於他國"
      ],
      "answer": "C",
      "type": "single",
      "audio": "",
      "score": 2
    },
    {
      "number": 17,
      "text": "小荃想造訪一處風景優美的祕境，但在抵達祕境的入口處，見有一告示牌寫著「上游水壩不定時洩洪，請勿進入溪谷以確保生命安全」，於是決定避開危險另覓他處。根據祕境附近的等高線地形圖（甲在水壩下游且位處溪谷處，乙位處支流較高處，丙、丁在水壩上游），甲、乙、丙、丁何者最可能為該祕境所在地點？<br><img src=\"/images/cap/114/社會/114_社會_試題.pdf-0005-08.webp\" style=\"max-width:100%; display:block; margin:10px 0;\"><br><img src=\"/images/cap/114/社會/114_社會_試題.pdf-0005-10.webp\" style=\"max-width:100%; display:block; margin:10px 0;\">",
      "passage": "",
      "options": [
        "甲",
        "乙",
        "丙",
        "丁"
      ],
      "answer": "A",
      "type": "single",
      "audio": "",
      "score": 2
    },
    {
      "number": 18,
      "text": "近年來由於新冠肺炎疫情造成嚴重的通貨膨脹，使得甲地的房價及物價高漲，影響其生活品質。此外，因為在鄰國的乙地1天的薪水，在甲地約1小時就賺得到，於是有一部分的甲地人搬至乙地居住，再利用遠距工作或每天通勤至甲地上班，藉以降低房租及生活消費。上述甲地與乙地依序最可能位於何國？",
      "passage": "",
      "options": [
        "法國、英國",
        "美國、墨西哥",
        "土耳其、希臘",
        "馬來西亞、新加坡"
      ],
      "answer": "B",
      "type": "single",
      "audio": "",
      "score": 2
    },
    {
      "number": 19,
      "text": "2022年世界及甲區域的人口年齡及性別資料中，甲區域呈現非常典型的金字塔型（低年齡層人口極多，高年齡層極少），而世界人口分布相對平均。根據人口組成判斷，甲區域最可能為下列何者？<br><img src=\"/images/cap/114/社會/114_社會_試題.pdf-0005-15.webp\" style=\"max-width:100%; display:block; margin:10px 0;\">",
      "passage": "",
      "options": [
        "歐洲",
        "北美洲",
        "東北亞",
        "漠南非洲"
      ],
      "answer": "D",
      "type": "single",
      "audio": "",
      "score": 2
    },
    {
      "number": 20,
      "text": "博物館展覽對臺灣歷史上某陶製漏斗狀工具使用方式的介紹：「1. 將黏稠的糖汁倒入，在底下放置漏罐承接糖蜜。 2. 乾燥後倒扣取出糖塊。」此種工具在十八至十九世紀之間，最多被用於圖(九)臺灣的何處？（圖中甲為北部、乙為中部、丙為西南部、丁為東南部）<br><img src=\"/images/cap/114/社會/114_社會_試題.pdf-0006-05.webp\" style=\"max-width:100%; display:block; margin:10px 0;\"><br><img src=\"/images/cap/114/社會/114_社會_試題.pdf-0006-06.webp\" style=\"max-width:100%; display:block; margin:10px 0;\">",
      "passage": "",
      "options": [
        "甲",
        "乙",
        "丙",
        "丁\n\n---"
      ],
      "answer": "C",
      "type": "single",
      "audio": "",
      "score": 2
    },
    {
      "number": 21,
      "text": "以下是學者對於中國史上某制度的論述：「此制度的基本涵義是指統治者透過任用非世襲的官員，建立中央集權的政府。這個制度初步發展於東周，在秦王朝統一天下後全面施行，隋唐等朝代都繼續沿用，也影響了周遭的日本、朝鮮，是中國重要的制度。」根據上述內容判斷，該制度最可能是下列何者？",
      "passage": "",
      "options": [
        "郡縣制度",
        "封建制度",
        "科舉制度",
        "九品官人法"
      ],
      "answer": "A",
      "type": "single",
      "audio": "",
      "score": 2
    },
    {
      "number": 22,
      "text": "某報紙報導的部分內容：「？ 大功告成。 陪都昨日熱烈慶祝。昨日重慶陽光燦爛，為舉行慶祝大會，政府機關、軍隊和民眾早就做了充分的準備，會場上懸掛著中、美、英、蘇四國領袖的巨幅畫像，象徵同盟國的勝利。會場上空繫著氣球，上書『世界和平』等字樣，市民都歡欣鼓舞的抬頭仰望。」標題中的「？」最適合填入下列何者？<br><img src=\"/images/cap/114/社會/114_社會_試題.pdf-0006-16.webp\" style=\"max-width:100%; display:block; margin:10px 0;\">",
      "passage": "",
      "options": [
        "辛亥革命",
        "北伐統一",
        "八年抗戰",
        "抗美援朝"
      ],
      "answer": "C",
      "type": "single",
      "audio": "",
      "score": 2
    },
    {
      "number": 23,
      "text": "「1989年8月19日，奧地利及匈牙利曾在邊界上相鄰的兩個小鎮間，舉辦一場野餐交流活動。活動中，兩鎮之間的木製國界圍籬會被打開三小時，象徵支持沒有隔閡的歐洲。然而，這場野餐會卻成為政治性的脫逃活動。當圍籬一打開，從其他國家特別前來此地的數百男女就迅速衝過邊界，逃離受到共產集團控制、實施計畫經濟的家鄉，抵達了『自由的歐洲』。」上述利用野餐脫逃的民眾，最可能來自歐洲地圖中甲、乙、丙、丁何地？（甲為東德/東歐區，乙為義大利，丙為法國，丁為英國）<br><img src=\"/images/cap/114/社會/114_社會_試題.pdf-0006-19.webp\" style=\"max-width:100%; display:block; margin:10px 0;\"><br><img src=\"/images/cap/114/社會/114_社會_試題.pdf-0006-20.webp\" style=\"max-width:100%; display:block; margin:10px 0;\">",
      "passage": "",
      "options": [
        "甲",
        "乙",
        "丙",
        "丁"
      ],
      "answer": "A",
      "type": "single",
      "audio": "",
      "score": 2
    },
    {
      "number": 24,
      "text": "某國中學生自治組織選舉前，針對二種投票方式進行調查，其中願意投票的人數比例如下表：\n\n| 年級 | 實體投票 (設置投票箱用實體選票圈選) | 網路投票 |\n|---|---|---|\n| 七 | 48% | 93% |\n| 八 | 49% | 95% |\n| 九 | 42% | 90% |\n\n根據上述內容判斷，關於此一調查結果，下列敘述何者最適當？",
      "passage": "",
      "options": [
        "實體投票比網路投票更能形成民意",
        "使用科技可能有洩漏個人資料的風險",
        "實體投票比網路投票更符合無記名原則",
        "使用科技能提升學生參與公共事務的程度"
      ],
      "answer": "D",
      "type": "single",
      "audio": "",
      "score": 2
    },
    {
      "number": 25,
      "text": "下列是某地方政府勞工局處理一件勞資糾紛的部分過程：\n勞工局：「根據貴公司的員工出勤紀錄，員工確實常加班工作，依法雇主應給付加班費。」\n雇主：「可是我又沒強迫員工留下來加班，有時候他們留在公司也不一定是為了工作，只是下班後不想那麼早離開而已。」\n勞工局：「依照《勞動事件法》規定，出勤紀錄內記載的勞工出勤時間，都預設勞工是經雇主同意而加班工作。若雇主認為員工並非因加班工作而留在公司，則須由雇主提出證明。」\n根據上述《勞動事件法》的規定判斷，下列何者最可能是當初立法時考量的理由？",
      "passage": "",
      "options": [
        "消除職場上出現的性別歧視行為",
        "確保勞工可維持基本的生活水準",
        "禁止超時工作以保障童工的身心健康",
        "平衡勞資雙方之間權力不對等的關係\n\n---"
      ],
      "answer": "D",
      "type": "single",
      "audio": "",
      "score": 2
    },
    {
      "number": 26,
      "text": "甲國在近三十年間，三種已婚女性的勞動力參與率（15歲以上民間人口中，已有工作者及正在找工作者的比率）折線圖顯示：尚無子女者勞動力參與率約 40% 成長至 75%；家中有未滿6歲子女者約 30% 成長至 60%；家中子女均在6歲以上者約 35% 成長至 45% 左右停滯。根據圖中資訊，可推論出該國社會存在下列何種現象？<br><img src=\"/images/cap/114/社會/114_社會_試題.pdf-0007-15.webp\" style=\"max-width:100%; display:block; margin:10px 0;\"><br><img src=\"/images/cap/114/社會/114_社會_試題.pdf-0007-17.webp\" style=\"max-width:100%; display:block; margin:10px 0;\">",
      "passage": "",
      "options": [
        "家務勞動影響了女性參與市場勞動的機會",
        "外籍配偶增多影響了該國女性的工作機會",
        "家庭型態變遷使女性承擔較多的家務勞動",
        "女性投入家務勞動的總時數比市場勞動多"
      ],
      "answer": "A",
      "type": "single",
      "audio": "",
      "score": 2
    },
    {
      "number": 27,
      "text": "土耳其扼黑海出入馬摩拉海的咽喉，因為原有天然航道（博斯普魯斯海峽）的航運交通量日益增加，政府計畫興建新運河。該計畫除了引發國內正反意見的討論外，也引起黑海周邊國家的高度關注。上述運河完工後所帶來的影響最可能為下列何者？<br><img src=\"/images/cap/114/社會/114_社會_試題.pdf-0008-02.webp\" style=\"max-width:100%; display:block; margin:10px 0;\"><br><img src=\"/images/cap/114/社會/114_社會_試題.pdf-0008-03.webp\" style=\"max-width:100%; display:block; margin:10px 0;\">",
      "passage": "",
      "options": [
        "土耳其將會喪失原有的「歐亞陸橋」稱號",
        "土耳其的經濟海域範圍將因此而大幅增加",
        "黑海的海洋生物進入馬摩拉海的機率下降",
        "船隻等候通過博斯普魯斯海峽的時間減少"
      ],
      "answer": "D",
      "type": "single",
      "audio": "",
      "score": 2
    },
    {
      "number": 28,
      "text": "某國的地理位置座標約為 103.83°E、1.33°N，島嶼最高點僅 163m。該國積極發展某一種綠色能源。根據資訊判斷，下列何者最可能為該國所發展的綠色能源及選擇的理由？<br><img src=\"/images/cap/114/社會/114_社會_試題.pdf-0008-06.webp\" style=\"max-width:100%; display:block; margin:10px 0;\"><br><img src=\"/images/cap/114/社會/114_社會_試題.pdf-0008-07.webp\" style=\"max-width:100%; display:block; margin:10px 0;\">",
      "passage": "",
      "options": [
        "水力；因雨量豐沛且山高水深，水力動能大",
        "太陽能；因位處太陽直射範圍，輻射強度大",
        "風力；因位於盛行西風帶，風力強勁且穩定",
        "海洋能；因北大西洋暖流流經，洋流動能大"
      ],
      "answer": "B",
      "type": "single",
      "audio": "",
      "score": 2
    },
    {
      "number": 29,
      "text": "小綸從網站上取得2021年中國各省級行政區年降水量資料，他以當年全國平均降水量691.6毫米作為標準，若省級行政區的年降水量低於此一數值，則在該區塗上深灰色。根據上述原則，小綸繪製出的地圖最可能為下列何者？（東南沿海降水多，西北內陸降水少）<br><img src=\"/images/cap/114/社會/114_社會_試題.pdf-0008-11.webp\" style=\"max-width:100%; display:block; margin:10px 0;\">",
      "passage": "",
      "options": [
        "塗黑區域在東南半部",
        "塗黑區域在西北半部",
        "塗黑區域在西南半部",
        "塗黑區域在東北半部"
      ],
      "answer": "B",
      "type": "single",
      "audio": "",
      "score": 2
    },
    {
      "number": 30,
      "text": "碳匯是指能夠吸收及儲存含碳化合物的天然或人工「倉庫」，如森林、草原、濕地、土壤、海洋等。為了達成2050年「碳中和」目標，各國除了減少二氧化碳的排放之外，也積極擴大國家的碳匯。根據上文所述，若要增加一國的碳匯，則下列何種方法最為適切？",
      "passage": "",
      "options": [
        "以焚林的方式，快速取得種植經濟作物的土地",
        "於屋頂上方設置太陽能發電板，增加電力供給",
        "恢復曾經消失的農地，採友善環境的耕作方式",
        "選用當地食材以減少運輸距離，降低食物里程\n\n---"
      ],
      "answer": "C",
      "type": "single",
      "audio": "",
      "score": 2
    },
    {
      "number": 31,
      "text": "莎綺去北大武山登山的時候，看到山路上有一些歷史建築，其中碑文寫道：「政府召募高砂族青年組成義勇隊，他們在南洋戰場上運輸糧食彈藥、攻克要塞、堅守陣地、突破包圍，展現忠義之心。今日在大武祠的附近，建碑祭祀陣亡的義勇隊英靈，期望他們的事蹟，能在高雄州的理蕃歷史上永遠流傳。 高雄州知事 撰」。根據碑文判斷，若莎綺上網檢索這些歷史建築興建的時局背景，最可能會出現下列何者？<br><img src=\"/images/cap/114/社會/114_社會_試題.pdf-0009-05.webp\" style=\"max-width:100%; display:block; margin:10px 0;\">",
      "passage": "",
      "options": [
        "強化皇民化運動的推展",
        "宣傳日俄戰爭即將勝利",
        "實施開山撫番推動漢化",
        "發起原住民族正名運動"
      ],
      "answer": "A",
      "type": "single",
      "audio": "",
      "score": 2
    },
    {
      "number": 32,
      "text": "理加頭目所屬部落與鄰近部落衝突頻繁，而荷蘭人未能妥善協助調停，心生不滿的他在日本人勸說下，帶族人前往日本尋求援助。理加返鄉後，立即遭到荷蘭人的監禁，進而引發日人挾持臺灣長官的衝突事件，更導致江戶幕府一度關閉荷蘭在日本的商館以作為制裁。上述事件最可能發生於下列何時何地？",
      "passage": "",
      "options": [
        "十六世紀的澎湖",
        "十七世紀的大員",
        "十八世紀的淡水",
        "十九世紀的卑南"
      ],
      "answer": "B",
      "type": "single",
      "audio": "",
      "score": 2
    },
    {
      "number": 33,
      "text": "某一時期臺灣鳳梨罐頭銷售至美國、日本、中國大陸及西德的官方統計數據（單位：箱）。\n\n| 年分 | 甲 | 乙 | 丙 | 丁 |\n|---|---|---|---|---|\n| 1946 | 0 | 0 | 0 | 60,696 |\n| 1950 | 38,134 | 203 | 0 | 0 |\n| 1955 | 182,000 | 33,836 | 153,963 | 0 |\n| 1960 | 269,338 | 676,098 | 737,723 | 0 |\n\n根據表中內容判斷，甲、乙、丙、丁何者最可能是中國大陸？",
      "passage": "",
      "options": [
        "甲",
        "乙",
        "丙",
        "丁"
      ],
      "answer": "D",
      "type": "single",
      "audio": "",
      "score": 2
    },
    {
      "number": 34,
      "text": "某大學公布欄所張貼的海報，主講者經歷為：1.法官 2.立法委員。根據圖中所列的演講者經歷判斷，下列何者最可能是他曾經行使過的職權？<br><img src=\"/images/cap/114/社會/114_社會_試題.pdf-0009-19.webp\" style=\"max-width:100%; display:block; margin:10px 0;\">",
      "passage": "",
      "options": [
        "為審核各機關送交的決算挑燈夜戰",
        "提請總統任命行政院所屬部會首長",
        "對司法院院長被提名人行使同意權",
        "在掌握事證後彈劾違法失職的法官"
      ],
      "answer": "C",
      "type": "single",
      "audio": "",
      "score": 2
    },
    {
      "number": 35,
      "text": "甲、乙二則資料呈現不同時代官方興建公共建設的相關情況：\n甲資料：統治者為了加強對國內各地的控制，便於運送物資及兵力，下令修鑿運河，強行徵召數百萬人民從事勞役。\n乙資料：某地方政府研擬興建社會住宅，當地議會要求依法召開公聽會聽取附近居民的意見，作為後續制定政策的參考。\n根據甲、乙二項資料判斷，關於不同時代官方興建公共建設作法的敘述，下列何者最適當？",
      "passage": "",
      "options": [
        "甲資料顯示當時的市場勞動權利受法律保障",
        "乙資料顯示當時的政府權力受到約束與制衡",
        "二則資料皆顯示公共建設以促進公平正義為主要考量",
        "二則資料皆顯示公共意見是經由大眾反覆討論而形成\n\n---"
      ],
      "answer": "B",
      "type": "single",
      "audio": "",
      "score": 2
    },
    {
      "number": 36,
      "text": "老師安排同學至地方法院參觀，並讓甲、乙、丙、丁四位同學在模擬法庭中扮演不同的角色。甲扮演檢察官，乙扮演被告，丙扮演辯護律師，丁扮演法官。根據我國法律規定及情境判斷，下列關於他們四人的臺詞，何者最適當？<br><img src=\"/images/cap/114/社會/114_社會_試題.pdf-0010-09.webp\" style=\"max-width:100%; display:block; margin:10px 0;\"><br><img src=\"/images/cap/114/社會/114_社會_試題.pdf-0010-10.webp\" style=\"max-width:100%; display:block; margin:10px 0;\">",
      "passage": "",
      "options": [
        "甲：我依據相關犯罪事證依法起訴乙",
        "乙：我承認錯誤，我會儘早償還借款",
        "丙：我希望甲審酌證據後判決乙無罪",
        "丁：我判決原告勝訴，撤銷行政處分"
      ],
      "answer": "A",
      "type": "single",
      "audio": "",
      "score": 2
    },
    {
      "number": 37,
      "text": "「社會企業」是近年頗受關注的概念，其中公司型的社會企業透過商業活動營利，以改善社會或環境問題為目標，並非以讓出資者獲利為唯一考量，而企業獲得的利潤，也將繼續投入改善社會或環境問題的商業活動，希望讓社會企業得以永續經營。下列何種作法與上述提及的企業經營模式最相符？",
      "passage": "",
      "options": [
        "運用低價策略創造企業優勢",
        "制定法律推行友善勞工政策",
        "提倡公平貿易幫助小農發展",
        "募集善心捐款扶助弱勢群體"
      ],
      "answer": "C",
      "type": "single",
      "audio": "",
      "score": 2
    },
    {
      "number": 38,
      "text": "某日新聞報導有位失智症患者將土地、房屋贈送給陌生人的糾紛，由於小明的爺爺是中度失智症患者，家人擔心爺爺也會做出類似行為而導致權益受損，便向律師諮詢。律師建議家屬可向法院提出聲請，對爺爺作出監護宣告。上述律師的建議內容應是希望達成下列何項法律效果？",
      "passage": "",
      "options": [
        "讓爺爺成為無行為能力人，以保障其財產",
        "讓爺爺成為限制行為能力人，以保障其財產",
        "讓爺爺成為無行為能力人，以保障其契約自由",
        "讓爺爺成為限制行為能力人，以保障其契約自由"
      ],
      "answer": "A",
      "type": "single",
      "audio": "",
      "score": 2
    },
    {
      "number": 39,
      "text": "2020年之前，臺灣與日本都面臨勞力短缺的問題，但日本提供比臺灣更高的薪資吸引國際移工，因此許多菲律賓籍移工較願意前往日本工作。不過2022年底時，許多在日本工作的菲律賓籍移工發現，雖然每個月都拿出相同金額的日幣兌換成菲律賓披索匯回家鄉，但年底換到的菲律賓披索卻比年初減少了約10%，因此他們打算改往澳洲工作。上述國際移工變更工作地的考量，其原因之一最可能為下列何者？",
      "passage": "",
      "options": [
        "菲律賓披索相對日幣升值",
        "菲律賓披索相對新臺幣貶值",
        "去臺灣工作的機會成本比去日本低",
        "去澳洲工作的機會成本比去日本高"
      ],
      "answer": "A",
      "type": "single",
      "audio": "",
      "score": 2
    },
    {
      "number": 40,
      "text": "「俄烏戰爭以來，歐盟對俄羅斯採取大規模的制裁措施，其中立陶宛於2022年6月18日，對經其領土進出俄羅斯加里寧格勒的貨運火車實施限制，因而引發俄羅斯強烈不滿。此一事件也凸顯出加里寧格勒的重要性。」地圖顯示加里寧格勒為位於立陶宛與波蘭之間、面臨波羅的海的俄羅斯飛地。根據上文及圖中資訊判斷，其重要性可用下列何者來說明？<br><img src=\"/images/cap/114/社會/114_社會_試題.pdf-0011-06.webp\" style=\"max-width:100%; display:block; margin:10px 0;\">",
      "passage": "",
      "options": [
        "作為俄羅斯與東北亞國家間的貿易前哨站",
        "為俄羅斯貨物經波羅的海出太平洋的港口",
        "位處俄羅斯天然氣輸送至芬蘭的最短路徑上",
        "是俄羅斯對抗北大西洋公約組織的軍事基地\n\n---"
      ],
      "answer": "D",
      "type": "single",
      "audio": "",
      "score": 2
    },
    {
      "number": 41,
      "text": "三個不同日期臺灣部分水庫的蓄水量百分比(%)如下表。這些水庫在2021年5月31日的蓄水量狀況（普遍極低），可能與下列何者關係最為密切？\n\n| 水庫名稱 | 所在行政區 | 2020年5月31日 | 2020年11月30日 | 2021年5月31日 |\n|---|---|---|---|---|\n| 翡翠水庫 | 新北市 | 80.9 | 94.6 | 62.1 |\n| 石門水庫 | 桃園市 | 49.7 | 67.4 | 12.5 |\n| 鯉魚潭水庫 | 苗栗縣 | 53.7 | 39.4 | 5.8 |\n| 德基水庫 | 臺中市 | 42.7 | 38.2 | 2.7 |\n| 曾文水庫 | 嘉義縣臺南市 | 27.7 | 23.1 | 4.1 |",
      "passage": "",
      "options": [
        "2021年梅雨鋒面提早報到",
        "2021年夏末對流雨較不旺盛",
        "2020年冬季迎風面的地形雨偏少",
        "2020年缺乏颱風帶來的豐沛雨量"
      ],
      "answer": "D",
      "type": "single",
      "audio": "",
      "score": 2
    },
    {
      "number": 42,
      "text": "某民意代表在服務處設立法律諮詢服務站，表(六)是2020年及2021年法律諮詢服務件數的統計資料（單位:件）。\n\n| 類型 | 2020年 | 2021年 |\n|---|---|---|\n| 民事事件 | 200 | 230 |\n| 刑事案件 | 180 | 150 |\n| 法律諮詢服務總數 | 380 | 380 |\n\n在2020年的刑事案件中，超過半數屬於告訴乃論，而2021年則有過半數的刑事案件屬於非告訴乃論。根據上述內容判斷，在2020年及2021年的諮詢服務中，可採調解方式處理的件數可能為下列何者？<br><img src=\"/images/cap/114/社會/114_社會_試題.pdf-0012-04.webp\" style=\"max-width:100%; display:block; margin:10px 0;\"><br><img src=\"/images/cap/114/社會/114_社會_試題.pdf-0012-09.webp\" style=\"max-width:100%; display:block; margin:10px 0;\"><br><img src=\"/images/cap/114/社會/114_社會_試題.pdf-0012-11.webp\" style=\"max-width:100%; display:block; margin:10px 0;\">",
      "passage": "",
      "options": [
        "2020年70件，2021年100件",
        "2020年100件，2021年70件",
        "2020年300件，2021年300件",
        "2020年330件，2021年330件\n\n**題組：43-45 題**\n位於墨西哥首都的國立人類學博物館，館藏以當地古文明的文物為主，大約有六十萬件。博物館的建築設計，呼應該地古文明信仰中的四種自然力量：風、火、水、土元素，充滿與大自然的共融感。\n一樓的展示廳為常設展，其中一塊區域專門展示當地古文明的農業。由於農業發展與宗教神話有密不可分的關係，因此展覽廳特別展示了保佑農業生產的神官雕像。神官雕像手中握著的物品，是原產於美洲的作物，也是當地古文明所倚重的主食。\n\n\n雖然博物館的收藏相當豐富，但在展品的說明上，受過去殖民歷史影響，大多僅採用今日當地的官方語文。若改善上述不足之處，勢必能造福更多到館參觀的外國旅客，增進對當地文化的了解。"
      ],
      "answer": "C",
      "type": "single",
      "audio": "",
      "score": 2
    },
    {
      "number": 43,
      "text": "下列何項展品，最可能屬於該博物館的主要館藏？<br><img src=\"/images/cap/114/社會/114_社會_試題.pdf-0012-14.webp\" style=\"max-width:100%; display:block; margin:10px 0;\">",
      "passage": "**題組：43-45 題**\n位於墨西哥首都的國立人類學博物館，館藏以當地古文明的文物為主，大約有六十萬件。博物館的建築設計，呼應該地古文明信仰中的四種自然力量：風、火、水、土元素，充滿與大自然的共融感。\n一樓的展示廳為常設展，其中一塊區域專門展示當地古文明的農業。由於農業發展與宗教神話有密不可分的關係，因此展覽廳特別展示了保佑農業生產的神官雕像。神官雕像手中握著的物品，是原產於美洲的作物，也是當地古文明所倚重的主食。\n\n\n雖然博物館的收藏相當豐富，但在展品的說明上，受過去殖民歷史影響，大多僅採用今日當地的官方語文。若改善上述不足之處，勢必能造福更多到館參觀的外國旅客，增進對當地文化的了解。<br><img src=\"/images/cap/114/社會/114_社會_試題.pdf-0012-09.webp\" style=\"max-width:100%; display:block; margin:10px 0;\"><br><img src=\"/images/cap/114/社會/114_社會_試題.pdf-0012-11.webp\" style=\"max-width:100%; display:block; margin:10px 0;\">",
      "options": [
        "巴比倫城門",
        "阿茲提克容器",
        "南島語族樹皮布",
        "因紐特獵具"
      ],
      "answer": "B",
      "type": "single",
      "audio": "",
      "score": 2
    },
    {
      "number": 44,
      "text": "文中提到神官雕像手中所持的原產於美洲的作物，最可能是下列何者？",
      "passage": "**題組：43-45 題**\n位於墨西哥首都的國立人類學博物館，館藏以當地古文明的文物為主，大約有六十萬件。博物館的建築設計，呼應該地古文明信仰中的四種自然力量：風、火、水、土元素，充滿與大自然的共融感。\n一樓的展示廳為常設展，其中一塊區域專門展示當地古文明的農業。由於農業發展與宗教神話有密不可分的關係，因此展覽廳特別展示了保佑農業生產的神官雕像。神官雕像手中握著的物品，是原產於美洲的作物，也是當地古文明所倚重的主食。\n\n\n雖然博物館的收藏相當豐富，但在展品的說明上，受過去殖民歷史影響，大多僅採用今日當地的官方語文。若改善上述不足之處，勢必能造福更多到館參觀的外國旅客，增進對當地文化的了解。",
      "options": [
        "玉米",
        "橄欖",
        "小麥",
        "稻米"
      ],
      "answer": "A",
      "type": "single",
      "audio": "",
      "score": 2
    },
    {
      "number": 45,
      "text": "文中博物館的展品說明，最可能以何種語文為主？",
      "passage": "**題組：43-45 題**\n位於墨西哥首都的國立人類學博物館，館藏以當地古文明的文物為主，大約有六十萬件。博物館的建築設計，呼應該地古文明信仰中的四種自然力量：風、火、水、土元素，充滿與大自然的共融感。\n一樓的展示廳為常設展，其中一塊區域專門展示當地古文明的農業。由於農業發展與宗教神話有密不可分的關係，因此展覽廳特別展示了保佑農業生產的神官雕像。神官雕像手中握著的物品，是原產於美洲的作物，也是當地古文明所倚重的主食。\n\n\n雖然博物館的收藏相當豐富，但在展品的說明上，受過去殖民歷史影響，大多僅採用今日當地的官方語文。若改善上述不足之處，勢必能造福更多到館參觀的外國旅客，增進對當地文化的了解。",
      "options": [
        "英文",
        "法文",
        "葡萄牙文",
        "西班牙文\n\n**題組：46-48 題**\n我國現行汽、機車車牌號碼的編碼規則，原則上每組號碼皆是由英文字母與阿拉伯數字組成，但在民意反應及諸多考量下，有些數字、英文字母或是特定組合，已不再使用於新發放的車牌。例如：數字的「4」，是因為其發音與「死」字相近，一般民眾認為觸霉頭而不願使用；英文字母的「I」、「O」不再被使用，是因為與數字「1」、「0」太相似；至於BAD、BUM、END等，則由於字母組合具有負面意涵，因此也加以排除。\n除此之外，政府也開放民眾可額外付費選擇號碼，有些民眾會想要擁有6666、8888、9999等特殊號碼的車牌，因此這些號碼的價格常遠高於其他車牌；也有另一些民眾只對與生日、特殊紀念日有關的號碼組合有興趣，因此選擇購買這些特定號碼。至於不在意車牌號碼的民眾，則可接受政府發放一般組合的車牌，無需額外支付選號費。但不論最後是選擇哪一個車牌號碼，汽、機車所有人都要將車牌懸掛在指定位置，違規者將被警察依《道路交通管理處罰條例》開罰。"
      ],
      "answer": "D",
      "type": "single",
      "audio": "",
      "score": 2
    },
    {
      "number": 46,
      "text": "多數國家使用0~9這十個數字作為車牌編碼的組合，但我國僅使用其中九個數字。根據文中內容判斷，其原因最可能為下列何者？",
      "passage": "**題組：46-48 題**\n我國現行汽、機車車牌號碼的編碼規則，原則上每組號碼皆是由英文字母與阿拉伯數字組成，但在民意反應及諸多考量下，有些數字、英文字母或是特定組合，已不再使用於新發放的車牌。例如：數字的「4」，是因為其發音與「死」字相近，一般民眾認為觸霉頭而不願使用；英文字母的「I」、「O」不再被使用，是因為與數字「1」、「0」太相似；至於BAD、BUM、END等，則由於字母組合具有負面意涵，因此也加以排除。\n除此之外，政府也開放民眾可額外付費選擇號碼，有些民眾會想要擁有6666、8888、9999等特殊號碼的車牌，因此這些號碼的價格常遠高於其他車牌；也有另一些民眾只對與生日、特殊紀念日有關的號碼組合有興趣，因此選擇購買這些特定號碼。至於不在意車牌號碼的民眾，則可接受政府發放一般組合的車牌，無需額外支付選號費。但不論最後是選擇哪一個車牌號碼，汽、機車所有人都要將車牌懸掛在指定位置，違規者將被警察依《道路交通管理處罰條例》開罰。",
      "options": [
        "倫理價值具有約束力",
        "民間習俗具有強制力",
        "法律規定受宗教信仰影響",
        "政府施政受社會規範影響"
      ],
      "answer": "D",
      "type": "single",
      "audio": "",
      "score": 2
    },
    {
      "number": 47,
      "text": "文中關於民眾選擇車牌號碼的敘述，最適合用來說明下列哪一觀點？",
      "passage": "**題組：46-48 題**\n我國現行汽、機車車牌號碼的編碼規則，原則上每組號碼皆是由英文字母與阿拉伯數字組成，但在民意反應及諸多考量下，有些數字、英文字母或是特定組合，已不再使用於新發放的車牌。例如：數字的「4」，是因為其發音與「死」字相近，一般民眾認為觸霉頭而不願使用；英文字母的「I」、「O」不再被使用，是因為與數字「1」、「0」太相似；至於BAD、BUM、END等，則由於字母組合具有負面意涵，因此也加以排除。\n除此之外，政府也開放民眾可額外付費選擇號碼，有些民眾會想要擁有6666、8888、9999等特殊號碼的車牌，因此這些號碼的價格常遠高於其他車牌；也有另一些民眾只對與生日、特殊紀念日有關的號碼組合有興趣，因此選擇購買這些特定號碼。至於不在意車牌號碼的民眾，則可接受政府發放一般組合的車牌，無需額外支付選號費。但不論最後是選擇哪一個車牌號碼，汽、機車所有人都要將車牌懸掛在指定位置，違規者將被警察依《道路交通管理處罰條例》開罰。",
      "options": [
        "廠商之間的價格競爭將使消費者受惠",
        "市場的競爭程度越高對消費者越有利",
        "負向誘因促使民眾的行為發生改變",
        "不同人對同一誘因的感受有所不同"
      ],
      "answer": "D",
      "type": "single",
      "audio": "",
      "score": 2
    },
    {
      "number": 48,
      "text": "某民眾的車牌被別人惡意拔走，導致他違反文末所述的規定而受罰。若該民眾對此處罰不服，依法採行下列何種處理方式最適當？<br><img src=\"/images/cap/114/社會/114_社會_試題.pdf-0014-02.webp\" style=\"max-width:100%; display:block; margin:10px 0;\">",
      "passage": "**題組：46-48 題**\n我國現行汽、機車車牌號碼的編碼規則，原則上每組號碼皆是由英文字母與阿拉伯數字組成，但在民意反應及諸多考量下，有些數字、英文字母或是特定組合，已不再使用於新發放的車牌。例如：數字的「4」，是因為其發音與「死」字相近，一般民眾認為觸霉頭而不願使用；英文字母的「I」、「O」不再被使用，是因為與數字「1」、「0」太相似；至於BAD、BUM、END等，則由於字母組合具有負面意涵，因此也加以排除。\n除此之外，政府也開放民眾可額外付費選擇號碼，有些民眾會想要擁有6666、8888、9999等特殊號碼的車牌，因此這些號碼的價格常遠高於其他車牌；也有另一些民眾只對與生日、特殊紀念日有關的號碼組合有興趣，因此選擇購買這些特定號碼。至於不在意車牌號碼的民眾，則可接受政府發放一般組合的車牌，無需額外支付選號費。但不論最後是選擇哪一個車牌號碼，汽、機車所有人都要將車牌懸掛在指定位置，違規者將被警察依《道路交通管理處罰條例》開罰。",
      "options": [
        "向中央立法機關提出訴願",
        "向地方行政機關提出請願",
        "透過行政救濟途徑維護權益",
        "透過刑事訴訟途徑維護權益\n\n**題組：49-51 題**\n巴斯人的祖先原本居住於伊朗高原一帶，七世紀上半葉，阿拉伯軍隊擊敗統治當地的薩珊王朝國王伊嗣俟，不願被穆斯林統治的人們遠離故鄉，遷徙至印度半島西部避難。此後數個世紀，伊斯蘭教勢力逐漸進入印度，但印度的穆斯林統治者對於不同的宗教和文化，表現出較為寬容的態度。這使巴斯人得以在印度從事貿易等行業，並世代信仰發源於伊朗高原的宗教。\n十七世紀後期，善於經商的巴斯人，開始與歐洲商人合作，既促進印度西部城市孟買等地的繁榮，也使得巴斯人隨著歐洲商人來到中國進行貿易。十八世紀後期至十九世紀中期，巴斯商人在歐洲殖民勢力對中國的貿易網絡之中，扮演重要角色，並與控制印度的殖民者一起在中國活動。當時巴斯商人留下許多會館與墓園，墓碑碑文刻有：「紀念 布爵治．廓德瓦 來自孟買的巴斯人 西元1850年 即『伊嗣俟』紀元 1219年辭世 得年36歲」即為一例。\n\n十九世紀中期以後，因為美國內戰導致紡織業原料短缺，以及蘇伊士運河開通促進航運事業發展等影響，巴斯商人傾向加強投資印度和歐洲的產業，而對中國的商貿佔比則逐漸下降。"
      ],
      "answer": "C",
      "type": "single",
      "audio": "",
      "score": 2
    },
    {
      "number": 49,
      "text": "巴斯人的宗教信仰，最可能是下列何者？",
      "passage": "**題組：49-51 題**\n巴斯人的祖先原本居住於伊朗高原一帶，七世紀上半葉，阿拉伯軍隊擊敗統治當地的薩珊王朝國王伊嗣俟，不願被穆斯林統治的人們遠離故鄉，遷徙至印度半島西部避難。此後數個世紀，伊斯蘭教勢力逐漸進入印度，但印度的穆斯林統治者對於不同的宗教和文化，表現出較為寬容的態度。這使巴斯人得以在印度從事貿易等行業，並世代信仰發源於伊朗高原的宗教。\n十七世紀後期，善於經商的巴斯人，開始與歐洲商人合作，既促進印度西部城市孟買等地的繁榮，也使得巴斯人隨著歐洲商人來到中國進行貿易。十八世紀後期至十九世紀中期，巴斯商人在歐洲殖民勢力對中國的貿易網絡之中，扮演重要角色，並與控制印度的殖民者一起在中國活動。當時巴斯商人留下許多會館與墓園，墓碑碑文刻有：「紀念 布爵治．廓德瓦 來自孟買的巴斯人 西元1850年 即『伊嗣俟』紀元 1219年辭世 得年36歲」即為一例。\n\n十九世紀中期以後，因為美國內戰導致紡織業原料短缺，以及蘇伊士運河開通促進航運事業發展等影響，巴斯商人傾向加強投資印度和歐洲的產業，而對中國的商貿佔比則逐漸下降。<br><img src=\"/images/cap/114/社會/114_社會_試題.pdf-0014-02.webp\" style=\"max-width:100%; display:block; margin:10px 0;\">",
      "options": [
        "祆教",
        "佛教",
        "猶太教",
        "基督教"
      ],
      "answer": "A",
      "type": "single",
      "audio": "",
      "score": 2
    },
    {
      "number": 50,
      "text": "十九世紀上半葉，巴斯人與中國商人的主要貿易模式，最可能是下列何者？",
      "passage": "**題組：49-51 題**\n巴斯人的祖先原本居住於伊朗高原一帶，七世紀上半葉，阿拉伯軍隊擊敗統治當地的薩珊王朝國王伊嗣俟，不願被穆斯林統治的人們遠離故鄉，遷徙至印度半島西部避難。此後數個世紀，伊斯蘭教勢力逐漸進入印度，但印度的穆斯林統治者對於不同的宗教和文化，表現出較為寬容的態度。這使巴斯人得以在印度從事貿易等行業，並世代信仰發源於伊朗高原的宗教。\n十七世紀後期，善於經商的巴斯人，開始與歐洲商人合作，既促進印度西部城市孟買等地的繁榮，也使得巴斯人隨著歐洲商人來到中國進行貿易。十八世紀後期至十九世紀中期，巴斯商人在歐洲殖民勢力對中國的貿易網絡之中，扮演重要角色，並與控制印度的殖民者一起在中國活動。當時巴斯商人留下許多會館與墓園，墓碑碑文刻有：「紀念 布爵治．廓德瓦 來自孟買的巴斯人 西元1850年 即『伊嗣俟』紀元 1219年辭世 得年36歲」即為一例。\n\n十九世紀中期以後，因為美國內戰導致紡織業原料短缺，以及蘇伊士運河開通促進航運事業發展等影響，巴斯商人傾向加強投資印度和歐洲的產業，而對中國的商貿佔比則逐漸下降。",
      "options": [
        "巴斯人賣瓷器到中國以換取茶葉",
        "巴斯人賣鴉片到中國以取得白銀",
        "巴斯人賣鹿皮到中國以獲得棉花",
        "巴斯人賣茶葉到中國以交換工業品"
      ],
      "answer": "B",
      "type": "single",
      "audio": "",
      "score": 2
    },
    {
      "number": 51,
      "text": "關於墓碑文字的解讀，下列何者最適當？<br><img src=\"/images/cap/114/社會/114_社會_試題.pdf-0015-02.webp\" style=\"max-width:100%; display:block; margin:10px 0;\">",
      "passage": "**題組：49-51 題**\n巴斯人的祖先原本居住於伊朗高原一帶，七世紀上半葉，阿拉伯軍隊擊敗統治當地的薩珊王朝國王伊嗣俟，不願被穆斯林統治的人們遠離故鄉，遷徙至印度半島西部避難。此後數個世紀，伊斯蘭教勢力逐漸進入印度，但印度的穆斯林統治者對於不同的宗教和文化，表現出較為寬容的態度。這使巴斯人得以在印度從事貿易等行業，並世代信仰發源於伊朗高原的宗教。\n十七世紀後期，善於經商的巴斯人，開始與歐洲商人合作，既促進印度西部城市孟買等地的繁榮，也使得巴斯人隨著歐洲商人來到中國進行貿易。十八世紀後期至十九世紀中期，巴斯商人在歐洲殖民勢力對中國的貿易網絡之中，扮演重要角色，並與控制印度的殖民者一起在中國活動。當時巴斯商人留下許多會館與墓園，墓碑碑文刻有：「紀念 布爵治．廓德瓦 來自孟買的巴斯人 西元1850年 即『伊嗣俟』紀元 1219年辭世 得年36歲」即為一例。\n\n十九世紀中期以後，因為美國內戰導致紡織業原料短缺，以及蘇伊士運河開通促進航運事業發展等影響，巴斯商人傾向加強投資印度和歐洲的產業，而對中國的商貿佔比則逐漸下降。",
      "options": [
        "當時類似的巴斯墓葬，多集中於今日山東青島一帶",
        "根據時間可確認，此人於《南京條約》簽訂前來華",
        "此人為孟買出身，顯示其生前主要與日本商行合作",
        "碑刻的紀年方式，反映巴斯人珍視薩珊王朝的歷史\n\n**題組：52-54 題**\n\n坐落在南大西洋的南喬治亞島，冰天雪地的環境下，島上仍孕育了為數眾多的海獅、象鼻海豹、國王企鵝和特有種鳥類。\n1775年庫克船長登島後，宣布其為英國領土並以當時的英王命名。二十世紀初該島設有數個捕鯨站，目前皆已廢棄。1927年，鄰近該島的甲國聲稱擁有該島主權，此領土紛紛成為日後與英國爆發戰爭的原因之一，1982年戰爭結束後，該島仍為英國所管轄。目前該島幾乎沒有常住人口，為觀光船行程的中繼站。\n2017年7月，一座面積約4,200平方公里的龐大冰山，脫離南極陸地後持續在海上漂流，地圖顯示該冰山於不同時間的位置（2017年7月於南極半島東側，2019年11月向北移動，2020年7月持續往南喬治亞島方向移動）。該冰山雖然持續崩裂、融化，但仍相當巨大，2020年科學家依據過去其他冰山漂流的軌跡，推測它極有可能撞上南喬治亞島，並研判可能產生的影響。"
      ],
      "answer": "D",
      "type": "single",
      "audio": "",
      "score": 2
    },
    {
      "number": 52,
      "text": "根據地圖與文中資訊判斷，鄰近南喬治亞島的甲國（與英國產生領土紛爭）應為下列何者？",
      "passage": "**題組：52-54 題**\n\n坐落在南大西洋的南喬治亞島，冰天雪地的環境下，島上仍孕育了為數眾多的海獅、象鼻海豹、國王企鵝和特有種鳥類。\n1775年庫克船長登島後，宣布其為英國領土並以當時的英王命名。二十世紀初該島設有數個捕鯨站，目前皆已廢棄。1927年，鄰近該島的甲國聲稱擁有該島主權，此領土紛紛成為日後與英國爆發戰爭的原因之一，1982年戰爭結束後，該島仍為英國所管轄。目前該島幾乎沒有常住人口，為觀光船行程的中繼站。\n2017年7月，一座面積約4,200平方公里的龐大冰山，脫離南極陸地後持續在海上漂流，地圖顯示該冰山於不同時間的位置（2017年7月於南極半島東側，2019年11月向北移動，2020年7月持續往南喬治亞島方向移動）。該冰山雖然持續崩裂、融化，但仍相當巨大，2020年科學家依據過去其他冰山漂流的軌跡，推測它極有可能撞上南喬治亞島，並研判可能產生的影響。<br><img src=\"/images/cap/114/社會/114_社會_試題.pdf-0015-02.webp\" style=\"max-width:100%; display:block; margin:10px 0;\">",
      "options": [
        "南非",
        "澳洲",
        "阿根廷",
        "紐西蘭"
      ],
      "answer": "C",
      "type": "single",
      "audio": "",
      "score": 2
    },
    {
      "number": 53,
      "text": "依據上文及地圖資訊判斷，該冰山漂流的方向應為下列何者？",
      "passage": "**題組：52-54 題**\n\n坐落在南大西洋的南喬治亞島，冰天雪地的環境下，島上仍孕育了為數眾多的海獅、象鼻海豹、國王企鵝和特有種鳥類。\n1775年庫克船長登島後，宣布其為英國領土並以當時的英王命名。二十世紀初該島設有數個捕鯨站，目前皆已廢棄。1927年，鄰近該島的甲國聲稱擁有該島主權，此領土紛紛成為日後與英國爆發戰爭的原因之一，1982年戰爭結束後，該島仍為英國所管轄。目前該島幾乎沒有常住人口，為觀光船行程的中繼站。\n2017年7月，一座面積約4,200平方公里的龐大冰山，脫離南極陸地後持續在海上漂流，地圖顯示該冰山於不同時間的位置（2017年7月於南極半島東側，2019年11月向北移動，2020年7月持續往南喬治亞島方向移動）。該冰山雖然持續崩裂、融化，但仍相當巨大，2020年科學家依據過去其他冰山漂流的軌跡，推測它極有可能撞上南喬治亞島，並研判可能產生的影響。",
      "options": [
        "東北向西南",
        "西南向東北",
        "東南向西北",
        "西北向東南"
      ],
      "answer": "B",
      "type": "single",
      "audio": "",
      "score": 2
    },
    {
      "number": 54,
      "text": "上述冰山若撞上南喬治亞島，其產生的影響最可能為下列何者？",
      "passage": "**題組：52-54 題**\n\n坐落在南大西洋的南喬治亞島，冰天雪地的環境下，島上仍孕育了為數眾多的海獅、象鼻海豹、國王企鵝和特有種鳥類。\n1775年庫克船長登島後，宣布其為英國領土並以當時的英王命名。二十世紀初該島設有數個捕鯨站，目前皆已廢棄。1927年，鄰近該島的甲國聲稱擁有該島主權，此領土紛紛成為日後與英國爆發戰爭的原因之一，1982年戰爭結束後，該島仍為英國所管轄。目前該島幾乎沒有常住人口，為觀光船行程的中繼站。\n2017年7月，一座面積約4,200平方公里的龐大冰山，脫離南極陸地後持續在海上漂流，地圖顯示該冰山於不同時間的位置（2017年7月於南極半島東側，2019年11月向北移動，2020年7月持續往南喬治亞島方向移動）。該冰山雖然持續崩裂、融化，但仍相當巨大，2020年科學家依據過去其他冰山漂流的軌跡，推測它極有可能撞上南喬治亞島，並研判可能產生的影響。",
      "options": [
        "巨浪侵襲島嶼陸地，阻礙工業發展",
        "附近海水鹽度上升，改變海洋生態",
        "威脅北美洲與非洲之間的船隻安全",
        "島嶼海岸遭受破壞，危及動物棲地"
      ],
      "answer": "D",
      "type": "single",
      "audio": "",
      "score": 2
    }
  ]
}