{
  "title": "115 學年度學科能力測驗 - 英文考科 (參考試卷)",
  "duration": 100,
  "questions": [
    {
      "number": 1,
      "text": "The mayor has such a ______ schedule that it takes weeks to arrange an interview with her.",
      "passage": "",
      "options": [
        "hasty",
        "tight",
        "diligent",
        "routine"
      ],
      "answer": "B",
      "type": "single",
      "score": 2
    },
    {
      "number": 2,
      "text": "Jane started as an ______ art designer, but now she has a professional studio of her own.",
      "passage": "",
      "options": [
        "official",
        "instant",
        "amateur",
        "elementary"
      ],
      "answer": "C",
      "type": "single",
      "score": 2
    },
    {
      "number": 3,
      "text": "The teaching ______ at the famous high school soon attracted more than a dozen well-qualified applicants.",
      "passage": "",
      "options": [
        "career",
        "vacancy",
        "expectation",
        "inspiration"
      ],
      "answer": "B",
      "type": "single",
      "score": 2
    },
    {
      "number": 4,
      "text": "Designed by a young engineer, the new product has created far more profit than ______ expected.",
      "passage": "",
      "options": [
        "initially",
        "genuinely",
        "alternatively",
        "fundamentally"
      ],
      "answer": "A",
      "type": "single",
      "score": 2
    },
    {
      "number": 5,
      "text": "It has been confirmed that a balanced ______ of fruit and vegetables is a key element to good health.",
      "passage": "",
      "options": [
        "dimension",
        "integration",
        "provision",
        "consumption"
      ],
      "answer": "D",
      "type": "single",
      "score": 2
    },
    {
      "number": 6,
      "text": "As a shy boy afraid of making public appearances, Timmy ______ the thought of speaking before large audiences.",
      "passage": "",
      "options": [
        "dreads",
        "stresses",
        "wanders",
        "escapes"
      ],
      "answer": "A",
      "type": "single",
      "score": 2
    },
    {
      "number": 7,
      "text": "To the newly-crowned winner of the piano competition, music is his life’s ______ which he has devoted himself to whole-heartedly.",
      "passage": "",
      "options": [
        "resource",
        "impact",
        "passion",
        "emphasis"
      ],
      "answer": "C",
      "type": "single",
      "score": 2
    },
    {
      "number": 8,
      "text": "The drunk driver who shouted at passers-by and ______ them with glass bottles was quickly arrested by the police.",
      "passage": "",
      "options": [
        "shattered",
        "assaulted",
        "overturned",
        "condemned"
      ],
      "answer": "B",
      "type": "single",
      "score": 2
    },
    {
      "number": 9,
      "text": "There were so many people at the bus station that I had to ______ my way through the crowd to board the bus in time.",
      "passage": "",
      "options": [
        "crash",
        "tumble",
        "elbow",
        "struggle"
      ],
      "answer": "C",
      "type": "single",
      "score": 2
    },
    {
      "number": 10,
      "text": "Deadly shootings on US campuses have raised ______ concerns about how to prevent such tragic incidents from happening again.",
      "passage": "",
      "options": [
        "swift",
        "brutal",
        "harsh",
        "grave"
      ],
      "answer": "D",
      "type": "single",
      "score": 2
    },
    {
      "number": 11,
      "text": "",
      "passage": "**二、綜合測驗（占10分）**\n\n**題組：11-15 題**\n<br><img src=\"/images/ceec/115/學測/英文/group11_15.webp\" style=\"max-width:100%; display:block; margin:10px 0;\">",
      "options": [
        "what is more",
        "it turns out",
        "in other words",
        "all in all"
      ],
      "answer": "B",
      "type": "single",
      "score": 2
    },
    {
      "number": 12,
      "text": "",
      "passage": "**題組：11-15 題**\n<br><img src=\"/images/ceec/115/學測/英文/group11_15.webp\" style=\"max-width:100%; display:block; margin:10px 0;\">",
      "options": [
        "demonstrate",
        "immigrate",
        "communicate",
        "manipulate"
      ],
      "answer": "C",
      "type": "single",
      "score": 2
    },
    {
      "number": 13,
      "text": "",
      "passage": "**題組：11-15 題**\n<br><img src=\"/images/ceec/115/學測/英文/group11_15.webp\" style=\"max-width:100%; display:block; margin:10px 0;\">",
      "options": [
        "doubts",
        "icons",
        "matches",
        "clues"
      ],
      "answer": "D",
      "type": "single",
      "score": 2
    },
    {
      "number": 14,
      "text": "",
      "passage": "**題組：11-15 題**\n<br><img src=\"/images/ceec/115/學測/英文/group11_15.webp\" style=\"max-width:100%; display:block; margin:10px 0;\">",
      "options": [
        "hardly surprising",
        "more acceptable",
        "truly important",
        "less likely"
      ],
      "answer": "D",
      "type": "single",
      "score": 2
    },
    {
      "number": 15,
      "text": "",
      "passage": "**題組：11-15 題**\n<br><img src=\"/images/ceec/115/學測/英文/group11_15.webp\" style=\"max-width:100%; display:block; margin:10px 0;\">",
      "options": [
        "responsive to",
        "annoyed at",
        "considerate of",
        "tolerant with"
      ],
      "answer": "A",
      "type": "single",
      "score": 2
    },
    {
      "number": 16,
      "text": "",
      "passage": "**題組：16-20 題**\n<br><img src=\"/images/ceec/115/學測/英文/group16_20.webp\" style=\"max-width:100%; display:block; margin:10px 0;\">",
      "options": [
        "accommodate",
        "compensate",
        "anticipate",
        "reinforce"
      ],
      "answer": "A",
      "type": "single",
      "score": 2
    },
    {
      "number": 17,
      "text": "",
      "passage": "**題組：16-20 題**\n<br><img src=\"/images/ceec/115/學測/英文/group16_20.webp\" style=\"max-width:100%; display:block; margin:10px 0;\">",
      "options": [
        "would hardly develop",
        "had yet to develop",
        "was fast developing",
        "had almost developed"
      ],
      "answer": "B",
      "type": "single",
      "score": 2
    },
    {
      "number": 18,
      "text": "",
      "passage": "**題組：16-20 題**\n<br><img src=\"/images/ceec/115/學測/英文/group16_20.webp\" style=\"max-width:100%; display:block; margin:10px 0;\">",
      "options": [
        "passed on to",
        "brought up as",
        "thought to have",
        "meant to be"
      ],
      "answer": "D",
      "type": "single",
      "score": 2
    },
    {
      "number": 19,
      "text": "",
      "passage": "**題組：16-20 題**\n<br><img src=\"/images/ceec/115/學測/英文/group16_20.webp\" style=\"max-width:100%; display:block; margin:10px 0;\">",
      "options": [
        "if so",
        "as such",
        "by then",
        "in that"
      ],
      "answer": "B",
      "type": "single",
      "score": 2
    },
    {
      "number": 20,
      "text": "",
      "passage": "**題組：16-20 題**\n<br><img src=\"/images/ceec/115/學測/英文/group16_20.webp\" style=\"max-width:100%; display:block; margin:10px 0;\">",
      "options": [
        "a widely known delicacy",
        "an intimate romantic dinner",
        "a joyful social activity",
        "an amazing local cuisine"
      ],
      "answer": "C",
      "type": "single",
      "score": 2
    },
    {
      "number": 21,
      "text": "請選擇第 21 格的答案。",
      "passage": "**三、文意選填（占10分）**\n\n**題組：21-30 題**\n<br><img src=\"/images/ceec/115/學測/英文/group21_30.webp\" style=\"max-width:100%; display:block; margin:10px 0;\">",
      "options": [
        "retain",
        "depend on",
        "atmosphere",
        "delay",
        "unproductive",
        "risk",
        "function",
        "minimal",
        "dramatic",
        "point to"
      ],
      "answer": "E",
      "type": "single",
      "score": 2
    },
    {
      "number": 22,
      "text": "請選擇第 22 格的答案。",
      "passage": "**題組：21-30 題**\n<br><img src=\"/images/ceec/115/學測/英文/group21_30.webp\" style=\"max-width:100%; display:block; margin:10px 0;\">",
      "options": [
        "retain",
        "depend on",
        "atmosphere",
        "delay",
        "unproductive",
        "risk",
        "function",
        "minimal",
        "dramatic",
        "point to"
      ],
      "answer": "G",
      "type": "single",
      "score": 2
    },
    {
      "number": 23,
      "text": "請選擇第 23 格的答案。",
      "passage": "**題組：21-30 題**\n<br><img src=\"/images/ceec/115/學測/英文/group21_30.webp\" style=\"max-width:100%; display:block; margin:10px 0;\">",
      "options": [
        "retain",
        "depend on",
        "atmosphere",
        "delay",
        "unproductive",
        "risk",
        "function",
        "minimal",
        "dramatic",
        "point to"
      ],
      "answer": "F",
      "type": "single",
      "score": 2
    },
    {
      "number": 24,
      "text": "請選擇第 24 格的答案。",
      "passage": "**題組：21-30 題**\n<br><img src=\"/images/ceec/115/學測/英文/group21_30.webp\" style=\"max-width:100%; display:block; margin:10px 0;\">",
      "options": [
        "retain",
        "depend on",
        "atmosphere",
        "delay",
        "unproductive",
        "risk",
        "function",
        "minimal",
        "dramatic",
        "point to"
      ],
      "answer": "D",
      "type": "single",
      "score": 2
    },
    {
      "number": 25,
      "text": "請選擇第 25 格的答案。",
      "passage": "**題組：21-30 題**\n<br><img src=\"/images/ceec/115/學測/英文/group21_30.webp\" style=\"max-width:100%; display:block; margin:10px 0;\">",
      "options": [
        "retain",
        "depend on",
        "atmosphere",
        "delay",
        "unproductive",
        "risk",
        "function",
        "minimal",
        "dramatic",
        "point to"
      ],
      "answer": "A",
      "type": "single",
      "score": 2
    },
    {
      "number": 26,
      "text": "請選擇第 26 格的答案。",
      "passage": "**題組：21-30 題**\n<br><img src=\"/images/ceec/115/學測/英文/group21_30.webp\" style=\"max-width:100%; display:block; margin:10px 0;\">",
      "options": [
        "retain",
        "depend on",
        "atmosphere",
        "delay",
        "unproductive",
        "risk",
        "function",
        "minimal",
        "dramatic",
        "point to"
      ],
      "answer": "J",
      "type": "single",
      "score": 2
    },
    {
      "number": 27,
      "text": "請選擇第 27 格的答案。",
      "passage": "**題組：21-30 題**\n<br><img src=\"/images/ceec/115/學測/英文/group21_30.webp\" style=\"max-width:100%; display:block; margin:10px 0;\">",
      "options": [
        "retain",
        "depend on",
        "atmosphere",
        "delay",
        "unproductive",
        "risk",
        "function",
        "minimal",
        "dramatic",
        "point to"
      ],
      "answer": "B",
      "type": "single",
      "score": 2
    },
    {
      "number": 28,
      "text": "請選擇第 28 格的答案。",
      "passage": "**題組：21-30 題**\n<br><img src=\"/images/ceec/115/學測/英文/group21_30.webp\" style=\"max-width:100%; display:block; margin:10px 0;\">",
      "options": [
        "retain",
        "depend on",
        "atmosphere",
        "delay",
        "unproductive",
        "risk",
        "function",
        "minimal",
        "dramatic",
        "point to"
      ],
      "answer": "I",
      "type": "single",
      "score": 2
    },
    {
      "number": 29,
      "text": "請選擇第 29 格的答案。",
      "passage": "**題組：21-30 題**\n<br><img src=\"/images/ceec/115/學測/英文/group21_30.webp\" style=\"max-width:100%; display:block; margin:10px 0;\">",
      "options": [
        "retain",
        "depend on",
        "atmosphere",
        "delay",
        "unproductive",
        "risk",
        "function",
        "minimal",
        "dramatic",
        "point to"
      ],
      "answer": "H",
      "type": "single",
      "score": 2
    },
    {
      "number": 30,
      "text": "請選擇第 30 格的答案。",
      "passage": "**題組：21-30 題**\n<br><img src=\"/images/ceec/115/學測/英文/group21_30.webp\" style=\"max-width:100%; display:block; margin:10px 0;\">",
      "options": [
        "retain",
        "depend on",
        "atmosphere",
        "delay",
        "unproductive",
        "risk",
        "function",
        "minimal",
        "dramatic",
        "point to"
      ],
      "answer": "C",
      "type": "single",
      "score": 2
    },
    {
      "number": 31,
      "text": "請選擇第 31 格的答案。",
      "passage": "**四 、 篇 章 結 構 （ 占 8分 ）**\n\n**題組：31-34 題**\n<br><img src=\"/images/ceec/115/學測/英文/group31_34.webp\" style=\"max-width:100%; display:block; margin:10px 0;\">",
      "options": [
        "Another crucial factor is a society’s immigration diversity.",
        "Various factors have thus contributed to the phenomenon of smiling.",
        "For most of recorded human history, the open smile has been deeply unfashionable.",
        "A genuine smile indicates contentment, while a forced smile suggests underlying distress.",
        "In fact, there is a well-known Russian proverb that goes, “Smiling with no reason is a sign of stupidity.”"
      ],
      "answer": "C",
      "type": "single",
      "score": 2,
      "dropdown": true
    },
    {
      "number": 32,
      "text": "請選擇第 32 格的答案.",
      "passage": "**題組：31-34 題**\n<br><img src=\"/images/ceec/115/學測/英文/group31_34.webp\" style=\"max-width:100%; display:block; margin:10px 0;\">",
      "options": [
        "Another crucial factor is a society’s immigration diversity.",
        "Various factors have thus contributed to the phenomenon of smiling.",
        "For most of recorded human history, the open smile has been deeply unfashionable.",
        "A genuine smile indicates contentment, while a forced smile suggests underlying distress.",
        "In fact, there is a well-known Russian proverb that goes, “Smiling with no reason is a sign of stupidity.”"
      ],
      "answer": "E",
      "type": "single",
      "score": 2,
      "dropdown": true
    },
    {
      "number": 33,
      "text": "請選擇第 33 格的答案。",
      "passage": "**題組：31-34 題**\n<br><img src=\"/images/ceec/115/學測/英文/group31_34.webp\" style=\"max-width:100%; display:block; margin:10px 0;\">",
      "options": [
        "Another crucial factor is a society’s immigration diversity.",
        "Various factors have thus contributed to the phenomenon of smiling.",
        "For most of recorded human history, the open smile has been deeply unfashionable.",
        "A genuine smile indicates contentment, while a forced smile suggests underlying distress.",
        "In fact, there is a well-known Russian proverb that goes, “Smiling with no reason is a sign of stupidity.”"
      ],
      "answer": "A",
      "type": "single",
      "score": 2,
      "dropdown": true
    },
    {
      "number": 34,
      "text": "請選擇第 34 格的答案。",
      "passage": "**題組：31-34 題**\n<br><img src=\"/images/ceec/115/學測/英文/group31_34.webp\" style=\"max-width:100%; display:block; margin:10px 0;\">",
      "options": [
        "Another crucial factor is a society’s immigration diversity.",
        "Various factors have thus contributed to the phenomenon of smiling.",
        "For most of recorded human history, the open smile has been deeply unfashionable.",
        "A genuine smile indicates contentment, while a forced smile suggests underlying distress.",
        "In fact, there is a well-known Russian proverb that goes, “Smiling with no reason is a sign of stupidity.”"
      ],
      "answer": "B",
      "type": "single",
      "score": 2,
      "dropdown": true
    },
    {
      "number": 35,
      "text": "What is this passage mainly about?",
      "passage": "**五 、 閱 讀 測 驗 （ 占 24分 ）**\n\n**題組：35-38 題**\n<br><img src=\"/images/ceec/115/學測/英文/group35_38.webp\" style=\"max-width:100%; display:block; margin:10px 0;\">",
      "options": [
        "A renowned Antarctic explorer.",
        "The extreme weather in Antarctica.",
        "A challenging voyage to Antarctica.",
        "The amazing discovery of a sunken ship."
      ],
      "answer": "C",
      "type": "single",
      "score": 2
    },
    {
      "number": 36,
      "text": "Which of the following idioms is closest in meaning to “exacerbated the situation” in the third paragraph?",
      "passage": "**題組：35-38 題**\n<br><img src=\"/images/ceec/115/學測/英文/group35_38.webp\" style=\"max-width:100%; display:block; margin:10px 0;\">",
      "options": [
        "Broke the ice.",
        "Cost an arm and a leg.",
        "Missed the boat.",
        "Added fuel to the fire."
      ],
      "answer": "D",
      "type": "single",
      "score": 2
    },
    {
      "number": 37,
      "text": "According to the passage, which of the following is true about Shackleton and his Antarctic expedition?",
      "passage": "**題組：35-38 題**\n<br><img src=\"/images/ceec/115/學測/英文/group35_38.webp\" style=\"max-width:100%; display:block; margin:10px 0;\">",
      "options": [
        "His journey lasted more than two years.",
        "He was the first man to cross over the Antarctic.",
        "His team camped out on Elephant Island for five months.",
        "He sent five crew members on a lifeboat to get help from a whaling station."
      ],
      "answer": "A",
      "type": "single",
      "score": 2
    },
    {
      "number": 38,
      "text": "Which of the following shows the correct route of the Endurance after leaving South Georgia?",
      "passage": "**題組：35-38 題**\n<br><img src=\"/images/ceec/115/學測/英文/group35_38.webp\" style=\"max-width:100%; display:block; margin:10px 0;\">",
      "options": [
        "<br><img src=\"/images/ceec/115/學測/英文/q38_A.webp\" style=\"max-width:100%; display:block; margin:10px 0;\">",
        "<br><img src=\"/images/ceec/115/學測/英文/q38_B.webp\" style=\"max-width:100%; display:block; margin:10px 0;\">",
        "<br><img src=\"/images/ceec/115/學測/英文/q38_C.webp\" style=\"max-width:100%; display:block; margin:10px 0;\">",
        "<br><img src=\"/images/ceec/115/學測/英文/q38_D.webp\" style=\"max-width:100%; display:block; margin:10px 0;\">"
      ],
      "answer": "C",
      "type": "single",
      "score": 2
    },
    {
      "number": 39,
      "text": "Which question can the passage answer?",
      "passage": "**題組：39-42 題**\n<br><img src=\"/images/ceec/115/學測/英文/group39_42.webp\" style=\"max-width:100%; display:block; margin:10px 0;\">",
      "options": [
        "Where was the first spiral staircase constructed?",
        "Who was the first designer of the spiral staircase?",
        "What is the world’s most famous spiral staircase?",
        "Why is the spiral staircase popular in modern times?"
      ],
      "answer": "D",
      "type": "single",
      "score": 2
    },
    {
      "number": 40,
      "text": "What does “them” in the third paragraph refer to?",
      "passage": "**題組：39-42 題**\n<br><img src=\"/images/ceec/115/學測/英文/group39_42.webp\" style=\"max-width:100%; display:block; margin:10px 0;\">",
      "options": [
        "Stairs.",
        "Confines.",
        "Attackers.",
        "Defenders."
      ],
      "answer": "A",
      "type": "single",
      "score": 2
    },
    {
      "number": 41,
      "text": "According to the passage, which is a correct time sequence of the materials used in making spiral staircases?",
      "passage": "**題組：39-42 題**\n<br><img src=\"/images/ceec/115/學測/英文/group39_42.webp\" style=\"max-width:100%; display:block; margin:10px 0;\">",
      "options": [
        "stone → iron → steel → glass",
        "stone → wood → iron → steel",
        "iron → marble → wood → glass",
        "marble → wood → stone → concrete"
      ],
      "answer": "A",
      "type": "single",
      "score": 2
    },
    {
      "number": 42,
      "text": "Which of the following statements can be inferred about spiral staircases in the Medieval Ages?",
      "passage": "**題組：39-42 題**\n<br><img src=\"/images/ceec/115/學測/英文/group39_42.webp\" style=\"max-width:100%; display:block; margin:10px 0;\">",
      "options": [
        "The staircase was too narrow to allow any quick retreat.",
        "The clockwise design favored right-handed castle defenders.",
        "The uneven steps made it easier to ascend than descend the stairs.",
        "The staircase was dark enough for defenders to hide from attackers."
      ],
      "answer": "B",
      "type": "single",
      "score": 2
    },
    {
      "number": 43,
      "text": "What is the passage mainly about?",
      "passage": "**題組：43-46 題**\n<br><img src=\"/images/ceec/115/學測/英文/group43_46.webp\" style=\"max-width:100%; display:block; margin:10px 0;\">",
      "options": [
        "Why east is referred to as the “Orient.”",
        "How maps differ from GPS in function.",
        "How map orientation evolved over time.",
        "Why maps were important during the age of exploration."
      ],
      "answer": "C",
      "type": "single",
      "score": 2
    },
    {
      "number": 44,
      "text": "What does “this” refer to in the second paragraph?",
      "passage": "**題組：43-46 題**\n<br><img src=\"/images/ceec/115/學測/英文/group43_46.webp\" style=\"max-width:100%; display:block; margin:10px 0;\">",
      "options": [
        "The word dakshina.",
        "Physical evidence.",
        "Ancient India.",
        "East-orientation of maps."
      ],
      "answer": "D",
      "type": "single",
      "score": 2
    },
    {
      "number": 45,
      "text": "Which of the following is closest in meaning to “a blip” in the last paragraph?",
      "passage": "**題組：43-46 題**\n<br><img src=\"/images/ceec/115/學測/英文/group43_46.webp\" style=\"max-width:100%; display:block; margin:10px 0;\">",
      "options": [
        "A temporary state.",
        "An urgent need.",
        "A critical decision.",
        "An advanced system."
      ],
      "answer": "A",
      "type": "single",
      "score": 2
    },
    {
      "number": 46,
      "text": "Which of the following statements is true?",
      "passage": "**題組：43-46 題**\n<br><img src=\"/images/ceec/115/學測/英文/group43_46.webp\" style=\"max-width:100%; display:block; margin:10px 0;\">",
      "options": [
        "Sailors took the North Star as their final destination.",
        "The GPS system has a fixed direction for orientation.",
        "South was placed at the top of maps in the pre-Biblical era.",
        "Old Islamic maps put south at the top for religious purposes."
      ],
      "answer": "D",
      "type": "single",
      "score": 2
    },
    {
      "number": 47,
      "text": "請填寫第47格的單詞：",
      "passage": "**第貳部分、混合題（占10分）**\n\n**題組：47-50 題**\nLocated along the sparkling coastline of the Pacific Ocean, Wonder Village is a famous indigenous district in eastern Taiwan. The historic village exhibits the traditional way of life of the tribe there. However, it does not live in the past. As numerous new restaurants and shops have sprung up in recent years, it has become not only a cultural center but also a unique commercial zone. The following six shops are examples of some of the specialty stores there.\n<br><img src=\"/images/ceec/115/學測/英文/group47_50.webp\" style=\"max-width:100%; display:block; margin:10px 0;\">\n<br><img src=\"/images/ceec/115/學測/英文/group47_50_abc.webp\" style=\"max-width:100%; display:block; margin:10px 0;\">\n<br><img src=\"/images/ceec/115/學測/英文/group47_50_def.webp\" style=\"max-width:100%; display:block; margin:10px 0;\">\n\n**題組：47-48 題**\n<br><img src=\"/images/ceec/115/學測/英文/q47_48_cloze.webp\" style=\"max-width:100%; display:block; margin:10px 0;\">",
      "options": [],
      "answer": "innovation",
      "type": "fill",
      "score": 2
    },
    {
      "number": 48,
      "text": "請填寫第48格的單詞：",
      "passage": "**題組：47-50 題**\nLocated along the sparkling coastline of the Pacific Ocean, Wonder Village is a famous indigenous district in eastern Taiwan. The historic village exhibits the traditional way of life of the tribe there. However, it does not live in the past. As numerous new restaurants and shops have sprung up in recent years, it has become not only a cultural center but also a unique commercial zone. The following six shops are examples of some of the specialty stores there.\n<br><img src=\"/images/ceec/115/學測/英文/group47_50.webp\" style=\"max-width:100%; display:block; margin:10px 0;\">\n<br><img src=\"/images/ceec/115/學測/英文/group47_50_abc.webp\" style=\"max-width:100%; display:block; margin:10px 0;\">\n<br><img src=\"/images/ceec/115/學測/英文/group47_50_def.webp\" style=\"max-width:100%; display:block; margin:10px 0;\">\n\n**題組：47-48 題**\n<br><img src=\"/images/ceec/115/學測/英文/q47_48_cloze.webp\" style=\"max-width:100%; display:block; margin:10px 0;\">",
      "options": [],
      "answer": "blended",
      "type": "fill",
      "score": 2
    },
    {
      "number": 49,
      "text": "<br><img src=\"/images/ceec/115/學測/英文/q49_prompt.webp\" style=\"max-width:100%; display:block; margin:10px 0;\">",
      "passage": "**題組：49-50 題**",
      "options": [
        "Oh Eco",
        "After Work",
        "Aroma Paradise",
        "Something Different",
        "Beyond World",
        "The Pinery"
      ],
      "answer": [
        "A",
        "D",
        "E"
      ],
      "type": "multi",
      "score": 2
    },
    {
      "number": 50,
      "text": "<br><img src=\"/images/ceec/115/學測/英文/q50_prompt.webp\" style=\"max-width:100%; display:block; margin:10px 0;\">",
      "passage": "**題組：49-50 題**",
      "options": [],
      "answer": "one of a kind",
      "type": "essay",
      "score": 2
    },
    {
      "number": 51,
      "text": "<br><img src=\"/images/ceec/115/學測/英文/part3_q51_prompt.webp\" style=\"max-width:100%; display:block; margin:10px 0;\">",
      "passage": "**題組：49-50 題**",
      "options": [],
      "answer": "Nowadays",
      "type": "essay",
      "score": 2
    },
    {
      "number": 52,
      "text": "<br><img src=\"/images/ceec/115/學測/英文/part3_q52_prompt.webp\" style=\"max-width:100%; display:block; margin:10px 0;\">",
      "passage": "**題組：49-50 題**",
      "options": [],
      "answer": "They divide students into different groups based on their English proficiency",
      "type": "essay",
      "score": 2
    },
    {
      "number": 53,
      "text": "<br><img src=\"/images/ceec/115/學測/英文/part3_composition_all.webp\" style=\"max-width:100%; display:block; margin:10px 0;\">",
      "passage": "**題組：49-50 題**",
      "options": [],
      "answer": "請依據提示完成作文。重點在於內容須符合題目要求，提供充分、具體之細節，句構語法及用字適切，拼字與標點符號使用得當。",
      "type": "essay",
      "score": 2
    }
  ]
}